{
  "posts" : {
    "2018" : {
      "Jan" : {
        "01" : {
          "07:30" : {
            "-LROPxyD8rvFPbHrTsRE" : {
              "category" : "Ball Games",
              "city" : "Haifa",
              "currentNumPlayers" : 5,
              "description" : "gshs",
              "desiredNumPlayers" : 33,
              "game" : "Soccer",
              "host_age" : 44,
              "userID" : "FHFSk6QE9HXCILYoQE9F1eX7fvI2",
              "user_name" : "z@z.mm"
            }
          }
        }
      },
      "Jul" : {
        "01" : {
          "00:00" : {
            "-LRNyMKc1M966xAe3LPD" : {
              "category" : "Ball Games",
              "city" : "Haifa",
              "currentNumPlayers" : 5,
              "description" : "jsks",
              "desiredNumPlayers" : 6,
              "game" : "Soccer",
              "host_age" : 44,
              "userID" : "FHFSk6QE9HXCILYoQE9F1eX7fvI2",
              "user_name" : "z@z.mm"
            }
          }
        }
      },
      "Nov" : {
        "15" : {
          "00:00" : {
            "-LRNyQubW0XIjOhPdccZ" : {
              "category" : "Ball Games",
              "city" : "Haifa",
              "currentNumPlayers" : 6,
              "description" : "hskso",
              "desiredNumPlayers" : 6,
              "game" : "Soccer",
              "host_age" : 44,
              "userID" : "FHFSk6QE9HXCILYoQE9F1eX7fvI2",
              "user_name" : "z@z.mm"
            }
          }
        },
        "16" : {
          "00:00" : {
            "-LRNz1NVodMSRX9Nn5I0" : {
              "category" : "Ball Games",
              "city" : "Haifa",
              "currentNumPlayers" : 3,
              "description" : "jdj",
              "desiredNumPlayers" : 6,
              "game" : "Basketball",
              "host_age" : 45,
              "userID" : "CEphnEaDLuWnjgQUsuSj40AutoC3",
              "user_name" : "k@k.mm"
            }
          }
        }
      }
    },
    "2019" : {
      "Jan" : {
        "01" : {
          "08:15" : {
            "-LRS1uYjKtlzJ7_SRKHc" : {
              "category" : "Workout",
              "city" : "Haifa",
              "currentNumPlayers" : 5,
              "description" : "xvj",
              "desiredNumPlayers" : 33,
              "game" : "Spinning",
              "host_age" : 44,
              "userID" : "FHFSk6QE9HXCILYoQE9F1eX7fvI2",
              "user_name" : "z@z.mm"
            }
          }
        }
      }
    }
  },
  "users" : {
    "CEphnEaDLuWnjgQUsuSj40AutoC3" : {
      "age" : "45",
      "attending" : {
        "2018" : {
          "Nov" : {
            "15" : {
              "00:00" : {
                "-LRNyQubW0XIjOhPdccZ" : {
                  "category" : "Ball Games",
                  "city" : "Haifa",
                  "currentNumPlayers" : 5,
                  "description" : "hskso",
                  "desiredNumPlayers" : 6,
                  "game" : "Soccer",
                  "host_age" : 44,
                  "userID" : "FHFSk6QE9HXCILYoQE9F1eX7fvI2",
                  "user_name" : "z@z.mm"
                }
              }
            },
            "16" : {
              "00:00" : {
                "-LRNz1NVodMSRX9Nn5I0" : {
                  "category" : "Ball Games",
                  "city" : "Haifa",
                  "currentNumPlayers" : 2,
                  "description" : "jdj",
                  "desiredNumPlayers" : 6,
                  "game" : "Basketball",
                  "host_age" : 45,
                  "userID" : "CEphnEaDLuWnjgQUsuSj40AutoC3",
                  "user_name" : "k@k.mm"
                }
              }
            }
          }
        }
      },
      "city" : "Eilat",
      "created" : {
        "2018" : {
          "Nov" : {
            "16" : {
              "00:00" : {
                "-LRNz1NVodMSRX9Nn5I0" : {
                  "category" : "Ball Games",
                  "city" : "Haifa",
                  "currentNumPlayers" : 2,
                  "description" : "jdj",
                  "desiredNumPlayers" : 6,
                  "game" : "Basketball",
                  "host_age" : 45,
                  "userID" : "CEphnEaDLuWnjgQUsuSj40AutoC3",
                  "user_name" : "k@k.mm"
                }
              }
            }
          }
        }
      },
      "recommended" : {
        "2019" : {
          "Jan" : {
            "01" : {
              "08:15" : {
                "-LRS1uYjKtlzJ7_SRKHc" : {
                  "category" : "Workout",
                  "game" : "Spinning",
                  "userID" : "FHFSk6QE9HXCILYoQE9F1eX7fvI2"
                }
              }
            }
          }
        }
      },
      "user_name" : "k@k.mm"
    },
    "FHFSk6QE9HXCILYoQE9F1eX7fvI2" : {
      "age" : 44,
      "attending" : {
        "2018" : {
          "Jan" : {
            "01" : {
              "07:30" : {
                "-LROPxyD8rvFPbHrTsRE" : {
                  "category" : "Ball Games",
                  "city" : "Haifa",
                  "currentNumPlayers" : 5,
                  "description" : "gshs",
                  "desiredNumPlayers" : 33,
                  "game" : "Soccer",
                  "host_age" : 44,
                  "userID" : "FHFSk6QE9HXCILYoQE9F1eX7fvI2",
                  "user_name" : "z@z.mm"
                }
              }
            }
          },
          "Jul" : {
            "01" : {
              "00:00" : {
                "-LRNyMKc1M966xAe3LPD" : {
                  "category" : "Ball Games",
                  "city" : "Haifa",
                  "currentNumPlayers" : 5,
                  "description" : "jsks",
                  "desiredNumPlayers" : 6,
                  "game" : "Soccer",
                  "host_age" : 44,
                  "userID" : "FHFSk6QE9HXCILYoQE9F1eX7fvI2",
                  "user_name" : "z@z.mm"
                }
              }
            }
          },
          "Nov" : {
            "15" : {
              "00:00" : {
                "-LRNyQubW0XIjOhPdccZ" : {
                  "category" : "Ball Games",
                  "city" : "Haifa",
                  "currentNumPlayers" : 5,
                  "description" : "hskso",
                  "desiredNumPlayers" : 6,
                  "game" : "Soccer",
                  "host_age" : 44,
                  "userID" : "FHFSk6QE9HXCILYoQE9F1eX7fvI2",
                  "user_name" : "z@z.mm"
                }
              }
            },
            "16" : {
              "00:00" : {
                "-LRNz1NVodMSRX9Nn5I0" : {
                  "category" : "Ball Games",
                  "city" : "Haifa",
                  "currentNumPlayers" : 2,
                  "description" : "jdj",
                  "desiredNumPlayers" : 6,
                  "game" : "Basketball",
                  "host_age" : 45,
                  "userID" : "CEphnEaDLuWnjgQUsuSj40AutoC3",
                  "user_name" : "k@k.mm"
                }
              }
            }
          }
        },
        "2019" : {
          "Jan" : {
            "01" : {
              "08:15" : {
                "-LRS1uYjKtlzJ7_SRKHc" : {
                  "category" : "Workout",
                  "city" : "Haifa",
                  "currentNumPlayers" : 5,
                  "description" : "xvj",
                  "desiredNumPlayers" : 33,
                  "game" : "Spinning",
                  "host_age" : 44,
                  "userID" : "FHFSk6QE9HXCILYoQE9F1eX7fvI2",
                  "user_name" : "z@z.mm"
                }
              }
            }
          }
        }
      },
      "city" : "Haifa",
      "created" : {
        "2018" : {
          "Jan" : {
            "01" : {
              "07:30" : {
                "-LROPxyD8rvFPbHrTsRE" : {
                  "category" : "Ball Games",
                  "city" : "Haifa",
                  "currentNumPlayers" : 5,
                  "description" : "gshs",
                  "desiredNumPlayers" : 33,
                  "game" : "Soccer",
                  "host_age" : 44,
                  "userID" : "FHFSk6QE9HXCILYoQE9F1eX7fvI2",
                  "user_name" : "z@z.mm"
                }
              }
            }
          },
          "Jul" : {
            "01" : {
              "00:00" : {
                "-LRNyMKc1M966xAe3LPD" : {
                  "category" : "Ball Games",
                  "city" : "Haifa",
                  "currentNumPlayers" : 5,
                  "description" : "jsks",
                  "desiredNumPlayers" : 6,
                  "game" : "Soccer",
                  "host_age" : 44,
                  "userID" : "FHFSk6QE9HXCILYoQE9F1eX7fvI2",
                  "user_name" : "z@z.mm"
                }
              }
            }
          },
          "Nov" : {
            "15" : {
              "00:00" : {
                "-LRNyQubW0XIjOhPdccZ" : {
                  "category" : "Ball Games",
                  "city" : "Haifa",
                  "currentNumPlayers" : 5,
                  "description" : "hskso",
                  "desiredNumPlayers" : 6,
                  "game" : "Soccer",
                  "host_age" : 44,
                  "userID" : "FHFSk6QE9HXCILYoQE9F1eX7fvI2",
                  "user_name" : "z@z.mm"
                }
              }
            }
          }
        },
        "2019" : {
          "Jan" : {
            "01" : {
              "08:15" : {
                "-LRS1uYjKtlzJ7_SRKHc" : {
                  "category" : "Workout",
                  "city" : "Haifa",
                  "currentNumPlayers" : 5,
                  "description" : "xvj",
                  "desiredNumPlayers" : 33,
                  "game" : "Spinning",
                  "host_age" : 44,
                  "userID" : "FHFSk6QE9HXCILYoQE9F1eX7fvI2",
                  "user_name" : "z@z.mm"
                }
              }
            }
          }
        }
      },
      "user_name" : "z@z.mm"
    }
  }
}
